mediajson/__init__.py
mediajson/_version.py
mediajson/decode.py
mediajson/encode.py
mediajson/immutable.py
mediajson/py.typed
mediajson/typing.py
mediajson-2.3.0.dist-info/LICENSE.md
mediajson-2.3.0.dist-info/METADATA
mediajson-2.3.0.dist-info/NOTICE.md
mediajson-2.3.0.dist-info/WHEEL
mediajson-2.3.0.dist-info/top_level.txt
mediajson-2.3.0.dist-info/RECORD
